LICENSE
MANIFEST.in
README.md
requirements.txt
setup.py
src/SpaceTravLR/__init__.py
src/SpaceTravLR/astronomer.py
src/SpaceTravLR/beta.py
src/SpaceTravLR/gene_factory.py
src/SpaceTravLR/oracles.py
src/SpaceTravLR/spaceship.py
src/SpaceTravLR/virtual_tissue.py
src/SpaceTravLR/visionary.py
src/SpaceTravLR.egg-info/PKG-INFO
src/SpaceTravLR.egg-info/SOURCES.txt
src/SpaceTravLR.egg-info/dependency_links.txt
src/SpaceTravLR.egg-info/requires.txt
src/SpaceTravLR.egg-info/top_level.txt
src/SpaceTravLR/models/__init__.py
src/SpaceTravLR/models/adapted_estimators.py
src/SpaceTravLR/models/bayesian_linear.py
src/SpaceTravLR/models/estimators.py
src/SpaceTravLR/models/parallel_estimators.py
src/SpaceTravLR/models/pixel_attention.py
src/SpaceTravLR/models/probabilistic_estimators.py
src/SpaceTravLR/models/spatial_map.py
src/SpaceTravLR/models/vit_blocks.py
src/SpaceTravLR/plotting/__init__.py
src/SpaceTravLR/plotting/beta_maps.py
src/SpaceTravLR/plotting/cartography.py
src/SpaceTravLR/plotting/layout.py
src/SpaceTravLR/plotting/location.py
src/SpaceTravLR/plotting/modplot.py
src/SpaceTravLR/plotting/niche.py
src/SpaceTravLR/plotting/quantify.py
src/SpaceTravLR/plotting/sankey.py
src/SpaceTravLR/plotting/shift.py
src/SpaceTravLR/tools/__init__.py
src/SpaceTravLR/tools/data.py
src/SpaceTravLR/tools/iwanthue.py
src/SpaceTravLR/tools/knn_smooth.py
src/SpaceTravLR/tools/network.py
src/SpaceTravLR/tools/utils.py
src/SpaceTravLR_data/__init__.py
src/celloracle_tmp/__init__.py
src/celloracle_tmp/helpers.py
src/celloracle_tmp/version.py
src/celloracle_tmp/applications/__init__.py
src/celloracle_tmp/applications/development_module.py
src/celloracle_tmp/applications/differentiation_flow.py
src/celloracle_tmp/applications/pseudotime.py
src/celloracle_tmp/applications/scatter_to_grid.py
src/celloracle_tmp/applications/systematic_analysis_helper.py
src/celloracle_tmp/applications/utility.py
src/celloracle_tmp/data/__init__.py
src/celloracle_tmp/data/config.py
src/celloracle_tmp/data/load_data.py
src/celloracle_tmp/data/load_promoter_base_GRN.py
src/celloracle_tmp/data_conversion/__init__.py
src/celloracle_tmp/data_conversion/process_seurat_object.py
