Metadata-Version: 2.4
Name: SpaceTravLR
Version: 0.1.16
Summary: Spatially perturbing Transcription factors, Ligands & Receptors
Keywords: spatial transcriptomics,microniche identification,cell-cell communication
Classifier: Development Status :: 3 - Alpha
Classifier: Intended Audience :: Science/Research
Classifier: Programming Language :: Python :: 3
Classifier: Programming Language :: Python :: 3.8
Classifier: Programming Language :: Python :: 3.9
Classifier: Programming Language :: Python :: 3.10
Classifier: Programming Language :: Python :: 3.11
Requires-Python: >=3.8
License-File: LICENSE
Requires-Dist: setuptools<81
Requires-Dist: networkx
Requires-Dist: pysal>=24.01
Requires-Dist: scanpy>=1.10.2
Requires-Dist: torchvision
Requires-Dist: pyarrow
Requires-Dist: enlighten
Requires-Dist: pyro-ppl
Requires-Dist: group-lasso
Requires-Dist: pqdm
Requires-Dist: magic-impute
Requires-Dist: wordcloud
Requires-Dist: easydict
Requires-Dist: torch
Requires-Dist: ipykernel
Requires-Dist: simple-slurm
Requires-Dist: igraph
Requires-Dist: genomepy
Requires-Dist: pybedtools
Requires-Dist: ipywidgets
Requires-Dist: commot
Requires-Dist: numpy==1.26
Dynamic: classifier
Dynamic: keywords
Dynamic: license-file
Dynamic: requires-dist
Dynamic: requires-python
Dynamic: summary
